carriage/__init__.py
carriage/array.py
carriage/lambda_.py
carriage/map.py
carriage/monad.py
carriage/optional.py
carriage/pipeline.py
carriage/repr.py
carriage/row.py
carriage/stream.py
carriage/streamtable.py
carriage-0.4.15.dist-info/LICENSE
carriage-0.4.15.dist-info/WHEEL
carriage-0.4.15.dist-info/METADATA
carriage-0.4.15.dist-info/RECORD
